safe_cmp/__init__.py
safe_cmp/safe_cmp.py
safe_cmp/test.py
safe_cmp-0.1.1.dist-info/METADATA
safe_cmp-0.1.1.dist-info/WHEEL
safe_cmp-0.1.1.dist-info/pbr.json
safe_cmp-0.1.1.dist-info/top_level.txt
safe_cmp-0.1.1.dist-info/RECORD
