Metadata-Version: 2.1
Name: safe-cmp
Version: 0.1.1
Summary: Safe comparisons (total ordering) for any object in Python 3
Home-page: https://github.com/wolever/python-safe_cmp
Author: David Wolever
Author-email: david@wolever.net
License: FreeBSD
Platform: UNKNOWN
Classifier: Programming Language :: Python
Classifier: Programming Language :: Python :: 3
Classifier: License :: OSI Approved :: BSD License
Provides-Extra: dev
Requires-Dist: parameterized ; extra == 'dev'
Requires-Dist: nose ; extra == 'dev'
